dkist_data_simulator/__init__.py
dkist_data_simulator/dataset.py
dkist_data_simulator/expansions.py
dkist_data_simulator/py.typed
dkist_data_simulator/schemas.py
dkist_data_simulator/spec122.py
dkist_data_simulator/util.py
dkist_data_simulator/version.py
dkist_data_simulator/data/README.rst
dkist_data_simulator/dataset_extras/__init__.py
dkist_data_simulator/dataset_extras/dse_core.py
dkist_data_simulator/dataset_extras/dse_cryo.py
dkist_data_simulator/dataset_extras/dse_dlnirsp.py
dkist_data_simulator/dataset_extras/dse_visp.py
dkist_data_simulator/spec214/__init__.py
dkist_data_simulator/spec214/core.py
dkist_data_simulator/spec214/cryo.py
dkist_data_simulator/spec214/dlnirsp.py
dkist_data_simulator/spec214/vbi.py
dkist_data_simulator/spec214/visp.py
dkist_data_simulator/spec214/vtf.py
dkist_data_simulator/tests/__init__.py
dkist_data_simulator/tests/conftest.py
dkist_data_simulator/tests/test_122.py
dkist_data_simulator/tests/test_214.py
dkist_data_simulator/tests/test_214_inventory.py
dkist_data_simulator/tests/test_dataset.py
dkist_data_simulator/tests/test_dataset_extras.py
dkist_data_simulator-5.5.0.dist-info/licenses/licenses/LICENSE.rst
dkist_data_simulator-5.5.0.dist-info/METADATA
dkist_data_simulator-5.5.0.dist-info/WHEEL
dkist_data_simulator-5.5.0.dist-info/top_level.txt
dkist_data_simulator-5.5.0.dist-info/RECORD
