Metadata-Version: 2.4
Name: dkist_data_simulator
Version: 5.5.0
Summary: A header generator and FITS file creator for DKIST data.
Home-page: 
Author: AURA / NSO
Author-email: stuart@cadair.com
License: BSD 3-Clause
License-File: licenses/LICENSE.rst
Requires-Dist: dkist-fits-specifications>=4.19.0
Requires-Dist: sqids
Requires-Dist: tqdm
Requires-Dist: sunpy
Requires-Dist: astropy>=7.0.0
Requires-Dist: scipy
Provides-Extra: all
Provides-Extra: test
Requires-Dist: pytest; extra == "test"
Requires-Dist: pytest-doctestplus; extra == "test"
Requires-Dist: pytest-cov; extra == "test"
Requires-Dist: dkist-inventory; extra == "test"
Requires-Dist: dkist-header-validator; extra == "test"
Provides-Extra: docs
Requires-Dist: sphinx; extra == "docs"
Requires-Dist: sphinx-automodapi; extra == "docs"
Requires-Dist: sphinx-autodoc-typehints; extra == "docs"
Dynamic: license-file
